odoo9_addon_product_gtin-9.0.1.0.1-nspkg.pth
odoo_addons/product_gtin/README.rst
odoo_addons/product_gtin/__init__.py
odoo_addons/product_gtin/__openerp__.py
odoo_addons/product_gtin/i18n/fr.po
odoo_addons/product_gtin/i18n/product_gtin.pot
odoo_addons/product_gtin/models/__init__.py
odoo_addons/product_gtin/models/abstract_ean.py
odoo_addons/product_gtin/models/product_product.py
odoo_addons/product_gtin/models/res_partner.py
odoo_addons/product_gtin/static/description/icon.png
odoo_addons/product_gtin/tests/__init__.py
odoo_addons/product_gtin/tests/test_product_gtin_functions.py
odoo_addons/product_gtin/views/product_view.xml
odoo9_addon_product_gtin-9.0.1.0.1.dist-info/METADATA
odoo9_addon_product_gtin-9.0.1.0.1.dist-info/WHEEL
odoo9_addon_product_gtin-9.0.1.0.1.dist-info/namespace_packages.txt
odoo9_addon_product_gtin-9.0.1.0.1.dist-info/top_level.txt
odoo9_addon_product_gtin-9.0.1.0.1.dist-info/RECORD
