Metadata-Version: 2.1
Name: odoo9-addon-product-gtin
Version: 9.0.1.0.1
Summary: This module provides checks and management to EAN codes
Home-page: http://www.chricar.at/ChriCar
Author: ChriCar Beteiligungs- und Beratungs- GmbH, Odoo Community Association (OCA), ACSONE SA/NV
Author-email: support@odoo-community.org
License: AGPL-3
Platform: UNKNOWN
Classifier: Programming Language :: Python
Classifier: Framework :: Odoo
Classifier: License :: OSI Approved :: GNU Affero General Public License v3
Requires-Python: ~=2.7
Requires-Dist: odoo (<9.1a,>=9.0a)
